[
	{
		"subCategoryId":"S9410",
		"subCategoryName":"S9410-宗教組織"
	},
	{
		"subCategoryId":"S9421",
		"subCategoryName":"S9421-工商業團體"
	},
	{
		"subCategoryId":"S9422",
		"subCategoryName":"S9422-專門職業團體"
	},
	{
		"subCategoryId":"S9423",
		"subCategoryName":"S9423-勞工團體"
	},
	{
		"subCategoryId":"S9424",
		"subCategoryName":"S9424-農民團體"
	},
	{
		"subCategoryId":"S9491",
		"subCategoryName":"S9491-政治團體"
	},
	{
		"subCategoryId":"S9499",
		"subCategoryName":"S9499-未分類其他組織"
	},
	{
		"subCategoryId":"S9511",
		"subCategoryName":"S9511-汽車維修業"
	},
	{
		"subCategoryId":"S9512",
		"subCategoryName":"S9512-汽車美容業"
	},
	{
		"subCategoryId":"S9521",
		"subCategoryName":"S9521-電腦及其週邊設備修理業"
	},
	{
		"subCategoryId":"S9522",
		"subCategoryName":"S9522-通訊傳播設備修理業"
	},
	{
		"subCategoryId":"S9523",
		"subCategoryName":"S9523-視聽電子產品及家用電器修理業"
	},
	{
		"subCategoryId":"S9591",
		"subCategoryName":"S9591-機車維修業"
	},
	{
		"subCategoryId":"S9599",
		"subCategoryName":"S9599-未分類其他個人及家庭用品維修業"
	},
	{
		"subCategoryId":"S9591",
		"subCategoryName":"S9591-機車維修業"
	},
	{
		"subCategoryId":"S9610",
		"subCategoryName":"S9610-洗衣業"
	},
	{
		"subCategoryId":"S9620",
		"subCategoryName":"S9620-理髮及美容業"
	},
	{
		"subCategoryId":"S9630",
		"subCategoryName":"S9630-殯葬服務業"
	},
	{
		"subCategoryId":"S9640",
		"subCategoryName":"S9640-家事服務業"
	},
	{
		"subCategoryId":"S9690",
		"subCategoryName":"S9690-其他個人服務業"
	}
]
